wheeltennis/__init__.py
wheeltennis/match.py
wheeltennis/plots.py
wheeltennis/testing.py
wheeltennis-1.4.1.dist-info/licenses/LICENSE
wheeltennis-1.4.1.dist-info/METADATA
wheeltennis-1.4.1.dist-info/WHEEL
wheeltennis-1.4.1.dist-info/top_level.txt
wheeltennis-1.4.1.dist-info/RECORD
