Metadata-Version: 2.4
Name: wheeltennis
Version: 1.4.1
Summary: Basic scripts for wheelchair tennis analysis
Home-page: https://gitlab.com/Thomas2016/wheeltennis
Download-URL: https://gitlab.com/Thomas2016/wheeltennis
Author: Thomas Rietveld
Author-email: t.rietveld@lboro.ac.uk
License: GNU GPLv3
Keywords: wheelchair tennis,sensor,IMUs
Classifier: Programming Language :: Python
Classifier: Intended Audience :: Science/Research
Classifier: Operating System :: OS Independent
License-File: LICENSE
Requires-Dist: numpy
Requires-Dist: seaborn
Requires-Dist: scipy>=1.2.0
Requires-Dist: pandas
Requires-Dist: matplotlib
Requires-Dist: worklab
Dynamic: author
Dynamic: author-email
Dynamic: classifier
Dynamic: description
Dynamic: download-url
Dynamic: home-page
Dynamic: keywords
Dynamic: license
Dynamic: license-file
Dynamic: requires-dist
Dynamic: summary
